{"meta":{"scope":"congressional","contest_type":"president","year":2012,"districts":9,"match_coverage_pct":98.91,"allocation":"county_area_weighted_from_statewide_contest"},"general":{"results":{"1":{"dem_votes":175924,"rep_votes":108839,"other_votes":4804,"total_votes":289567,"dem_candidate":"Barack Obama","rep_candidate":"Mitt Romney","margin":-67085,"margin_pct":-23.1673,"winner":"DEM","color":"#2563eb"},"2":{"dem_votes":122938,"rep_votes":153909,"other_votes":5821,"total_votes":282668,"dem_candidate":"Barack Obama","rep_candidate":"Mitt Romney","margin":30971,"margin_pct":10.9567,"winner":"REP","color":"#dc2626"},"3":{"dem_votes":101368,"rep_votes":170120,"other_votes":5545,"total_votes":277033,"dem_candidate":"Barack Obama","rep_candidate":"Mitt Romney","margin":68752,"margin_pct":24.8173,"winner":"REP","color":"#dc2626"},"4":{"dem_votes":95724,"rep_votes":170033,"other_votes":6773,"total_votes":272530,"dem_candidate":"Barack Obama","rep_candidate":"Mitt Romney","margin":74309,"margin_pct":27.2664,"winner":"REP","color":"#dc2626"},"5":{"dem_votes":117379,"rep_votes":178086,"other_votes":6594,"total_votes":302059,"dem_candidate":"Barack Obama","rep_candidate":"Mitt Romney","margin":60707,"margin_pct":20.0977,"winner":"REP","color":"#dc2626"},"6":{"dem_votes":131174,"rep_votes":167408,"other_votes":6696,"total_votes":305278,"dem_candidate":"Barack Obama","rep_candidate":"Mitt Romney","margin":36234,"margin_pct":11.8692,"winner":"REP","color":"#dc2626"},"7":{"dem_votes":151926,"rep_votes":95866,"other_votes":4327,"total_votes":252119,"dem_candidate":"Barack Obama","rep_candidate":"Mitt Romney","margin":-56060,"margin_pct":-22.2355,"winner":"DEM","color":"#2563eb"},"8":{"dem_votes":121053,"rep_votes":178534,"other_votes":7046,"total_votes":306633,"dem_candidate":"Barack Obama","rep_candidate":"Mitt Romney","margin":57481,"margin_pct":18.7459,"winner":"REP","color":"#dc2626"},"9":{"dem_votes":128717,"rep_votes":175049,"other_votes":7447,"total_votes":311213,"dem_candidate":"Barack Obama","rep_candidate":"Mitt Romney","margin":46332,"margin_pct":14.8876,"winner":"REP","color":"#dc2626"}}}}