{
  "meta": {
    "scope": "congressional",
    "contest_type": "secretary_of_state",
    "year": 2018,
    "districts": 9,
    "match_coverage_pct": 100.0,
    "allocation": "precinct_area_weighted_from_vtd20_precincts",
    "precinct_rows": 5151,
    "precinct_geom_match_pct": 57.76
  },
  "general": {
    "results": {
      "1": {
        "dem_votes": 347678,
        "rep_votes": 212200,
        "other_votes": 14316,
        "total_votes": 574194,
        "dem_candidate": "Jim Harper",
        "rep_candidate": "Connie Lawson",
        "margin": -135478,
        "margin_pct": -23.5945,
        "winner": "DEM",
        "color": "#2563eb"
      },
      "2": {
        "dem_votes": 93956,
        "rep_votes": 167888,
        "other_votes": 37165,
        "total_votes": 299009,
        "dem_candidate": "Jim Harper",
        "rep_candidate": "Connie Lawson",
        "margin": 73932,
        "margin_pct": 24.7257,
        "winner": "REP",
        "color": "#dc2626"
      },
      "3": {
        "dem_votes": 130879,
        "rep_votes": 233076,
        "other_votes": 25544,
        "total_votes": 389499,
        "dem_candidate": "Jim Harper",
        "rep_candidate": "Connie Lawson",
        "margin": 102197,
        "margin_pct": 26.2381,
        "winner": "REP",
        "color": "#dc2626"
      },
      "4": {
        "dem_votes": 123019,
        "rep_votes": 211802,
        "other_votes": 29752,
        "total_votes": 364573,
        "dem_candidate": "Jim Harper",
        "rep_candidate": "Connie Lawson",
        "margin": 88783,
        "margin_pct": 24.3526,
        "winner": "REP",
        "color": "#dc2626"
      },
      "5": {
        "dem_votes": 208407,
        "rep_votes": 339758,
        "other_votes": 18627,
        "total_votes": 566792,
        "dem_candidate": "Jim Harper",
        "rep_candidate": "Connie Lawson",
        "margin": 131351,
        "margin_pct": 23.1745,
        "winner": "REP",
        "color": "#dc2626"
      },
      "6": {
        "dem_votes": 99623,
        "rep_votes": 147350,
        "other_votes": 29160,
        "total_votes": 276133,
        "dem_candidate": "Jim Harper",
        "rep_candidate": "Connie Lawson",
        "margin": 47727,
        "margin_pct": 17.2841,
        "winner": "REP",
        "color": "#dc2626"
      },
      "7": {
        "dem_votes": 127719,
        "rep_votes": 79992,
        "other_votes": 6705,
        "total_votes": 214416,
        "dem_candidate": "Jim Harper",
        "rep_candidate": "Connie Lawson",
        "margin": -47727,
        "margin_pct": -22.2591,
        "winner": "DEM",
        "color": "#2563eb"
      },
      "8": {
        "dem_votes": 103731,
        "rep_votes": 170708,
        "other_votes": 61081,
        "total_votes": 335520,
        "dem_candidate": "Jim Harper",
        "rep_candidate": "Connie Lawson",
        "margin": 66977,
        "margin_pct": 19.9621,
        "winner": "REP",
        "color": "#dc2626"
      },
      "9": {
        "dem_votes": 158204,
        "rep_votes": 181336,
        "other_votes": 41857,
        "total_votes": 381397,
        "dem_candidate": "Jim Harper",
        "rep_candidate": "Connie Lawson",
        "margin": 23132,
        "margin_pct": 6.0651,
        "winner": "REP",
        "color": "#dc2626"
      }
    }
  }
}
