{
  "meta": {
    "scope": "state_house",
    "contest_type": "us_senate",
    "year": 2024,
    "districts": 100,
    "match_coverage_pct": 100,
    "allocation": "precinct_area_weighted_from_vtd20_precincts",
    "precinct_rows": 5030,
    "precinct_geom_match_pct": 64.17,
    "calibration": {
      "enabled": true,
      "method": "vote_share_from_calibration_csv_rescaled_to_total_votes",
      "calibration_csv": "Data/Calibration csvs/district-statistics state house 2024 us senate.csv",
      "calibration_scope": "state_house",
      "calibration_year": 2024,
      "calibration_contest_type": "us_senate",
      "generated_on": "2026-04-29",
      "districts_with_shares": 100,
      "districts_calibrated": 100,
      "districts_missing_shares": 0
    }
  },
  "general": {
    "results": {
      "1": {
        "dem_votes": 4979,
        "rep_votes": 2482,
        "other_votes": 175,
        "total_votes": 7636,
        "dem_candidate": "Valerie McCray",
        "rep_candidate": "Jim Banks",
        "margin": -2497,
        "margin_pct": -32.7004,
        "winner": "DEM",
        "color": "#2563eb"
      },
      "2": {
        "dem_votes": 10855,
        "rep_votes": 2358,
        "other_votes": 231,
        "total_votes": 13444,
        "dem_candidate": "Valerie McCray",
        "rep_candidate": "Jim Banks",
        "margin": -8497,
        "margin_pct": -63.2029,
        "winner": "DEM",
        "color": "#2563eb"
      },
      "3": {
        "dem_votes": 33452,
        "rep_votes": 18708,
        "other_votes": 1125,
        "total_votes": 53285,
        "dem_candidate": "Valerie McCray",
        "rep_candidate": "Jim Banks",
        "margin": -14744,
        "margin_pct": -27.6701,
        "winner": "DEM",
        "color": "#2563eb"
      },
      "4": {
        "dem_votes": 14902,
        "rep_votes": 18946,
        "other_votes": 680,
        "total_votes": 34528,
        "dem_candidate": "Valerie McCray",
        "rep_candidate": "Jim Banks",
        "margin": 4044,
        "margin_pct": 11.7122,
        "winner": "REP",
        "color": "#dc2626"
      },
      "5": {
        "dem_votes": 4560,
        "rep_votes": 5968,
        "other_votes": 192,
        "total_votes": 10720,
        "dem_candidate": "Valerie McCray",
        "rep_candidate": "Jim Banks",
        "margin": 1408,
        "margin_pct": 13.1343,
        "winner": "REP",
        "color": "#dc2626"
      },
      "6": {
        "dem_votes": 2751,
        "rep_votes": 1484,
        "other_votes": 104,
        "total_votes": 4339,
        "dem_candidate": "Valerie McCray",
        "rep_candidate": "Jim Banks",
        "margin": -1267,
        "margin_pct": -29.2003,
        "winner": "DEM",
        "color": "#2563eb"
      },
      "7": {
        "dem_votes": 31159,
        "rep_votes": 46080,
        "other_votes": 1665,
        "total_votes": 78904,
        "dem_candidate": "Valerie McCray",
        "rep_candidate": "Jim Banks",
        "margin": 14921,
        "margin_pct": 18.9103,
        "winner": "REP",
        "color": "#dc2626"
      },
      "8": {
        "dem_votes": 7347,
        "rep_votes": 6161,
        "other_votes": 266,
        "total_votes": 13774,
        "dem_candidate": "Valerie McCray",
        "rep_candidate": "Jim Banks",
        "margin": -1186,
        "margin_pct": -8.6104,
        "winner": "DEM",
        "color": "#2563eb"
      },
      "9": {
        "dem_votes": 14543,
        "rep_votes": 14023,
        "other_votes": 667,
        "total_votes": 29233,
        "dem_candidate": "Valerie McCray",
        "rep_candidate": "Jim Banks",
        "margin": -520,
        "margin_pct": -1.7788,
        "winner": "DEM",
        "color": "#2563eb"
      },
      "10": {
        "dem_votes": 13873,
        "rep_votes": 14916,
        "other_votes": 684,
        "total_votes": 29473,
        "dem_candidate": "Valerie McCray",
        "rep_candidate": "Jim Banks",
        "margin": 1043,
        "margin_pct": 3.5388,
        "winner": "REP",
        "color": "#dc2626"
      },
      "11": {
        "dem_votes": 19746,
        "rep_votes": 53493,
        "other_votes": 1755,
        "total_votes": 74994,
        "dem_candidate": "Valerie McCray",
        "rep_candidate": "Jim Banks",
        "margin": 33747,
        "margin_pct": 44.9996,
        "winner": "REP",
        "color": "#dc2626"
      },
      "12": {
        "dem_votes": 4065,
        "rep_votes": 3622,
        "other_votes": 148,
        "total_votes": 7835,
        "dem_candidate": "Valerie McCray",
        "rep_candidate": "Jim Banks",
        "margin": -443,
        "margin_pct": -5.6541,
        "winner": "DEM",
        "color": "#2563eb"
      },
      "13": {
        "dem_votes": 8678,
        "rep_votes": 21836,
        "other_votes": 882,
        "total_votes": 31396,
        "dem_candidate": "Valerie McCray",
        "rep_candidate": "Jim Banks",
        "margin": 13158,
        "margin_pct": 41.9098,
        "winner": "REP",
        "color": "#dc2626"
      },
      "14": {
        "dem_votes": 8487,
        "rep_votes": 3293,
        "other_votes": 177,
        "total_votes": 11957,
        "dem_candidate": "Valerie McCray",
        "rep_candidate": "Jim Banks",
        "margin": -5194,
        "margin_pct": -43.439,
        "winner": "DEM",
        "color": "#2563eb"
      },
      "15": {
        "dem_votes": 5631,
        "rep_votes": 8494,
        "other_votes": 196,
        "total_votes": 14321,
        "dem_candidate": "Valerie McCray",
        "rep_candidate": "Jim Banks",
        "margin": 2863,
        "margin_pct": 19.9916,
        "winner": "REP",
        "color": "#dc2626"
      },
      "16": {
        "dem_votes": 6782,
        "rep_votes": 21391,
        "other_votes": 812,
        "total_votes": 28985,
        "dem_candidate": "Valerie McCray",
        "rep_candidate": "Jim Banks",
        "margin": 14609,
        "margin_pct": 50.4019,
        "winner": "REP",
        "color": "#dc2626"
      },
      "17": {
        "dem_votes": 6918,
        "rep_votes": 20411,
        "other_votes": 623,
        "total_votes": 27952,
        "dem_candidate": "Valerie McCray",
        "rep_candidate": "Jim Banks",
        "margin": 13493,
        "margin_pct": 48.272,
        "winner": "REP",
        "color": "#dc2626"
      },
      "18": {
        "dem_votes": 6393,
        "rep_votes": 23707,
        "other_votes": 768,
        "total_votes": 30868,
        "dem_candidate": "Valerie McCray",
        "rep_candidate": "Jim Banks",
        "margin": 17314,
        "margin_pct": 56.0904,
        "winner": "REP",
        "color": "#dc2626"
      },
      "19": {
        "dem_votes": 14267,
        "rep_votes": 20795,
        "other_votes": 687,
        "total_votes": 35749,
        "dem_candidate": "Valerie McCray",
        "rep_candidate": "Jim Banks",
        "margin": 6528,
        "margin_pct": 18.2607,
        "winner": "REP",
        "color": "#dc2626"
      },
      "20": {
        "dem_votes": 9578,
        "rep_votes": 17988,
        "other_votes": 780,
        "total_votes": 28346,
        "dem_candidate": "Valerie McCray",
        "rep_candidate": "Jim Banks",
        "margin": 8410,
        "margin_pct": 29.6691,
        "winner": "REP",
        "color": "#dc2626"
      },
      "21": {
        "dem_votes": 6881,
        "rep_votes": 15185,
        "other_votes": 421,
        "total_votes": 22487,
        "dem_candidate": "Valerie McCray",
        "rep_candidate": "Jim Banks",
        "margin": 8304,
        "margin_pct": 36.928,
        "winner": "REP",
        "color": "#dc2626"
      },
      "22": {
        "dem_votes": 5551,
        "rep_votes": 20964,
        "other_votes": 775,
        "total_votes": 27290,
        "dem_candidate": "Valerie McCray",
        "rep_candidate": "Jim Banks",
        "margin": 15413,
        "margin_pct": 56.4786,
        "winner": "REP",
        "color": "#dc2626"
      },
      "23": {
        "dem_votes": 5576,
        "rep_votes": 16699,
        "other_votes": 663,
        "total_votes": 22938,
        "dem_candidate": "Valerie McCray",
        "rep_candidate": "Jim Banks",
        "margin": 11123,
        "margin_pct": 48.4916,
        "winner": "REP",
        "color": "#dc2626"
      },
      "24": {
        "dem_votes": 15972,
        "rep_votes": 21337,
        "other_votes": 793,
        "total_votes": 38102,
        "dem_candidate": "Valerie McCray",
        "rep_candidate": "Jim Banks",
        "margin": 5365,
        "margin_pct": 14.0806,
        "winner": "REP",
        "color": "#dc2626"
      },
      "25": {
        "dem_votes": 16379,
        "rep_votes": 20157,
        "other_votes": 944,
        "total_votes": 37480,
        "dem_candidate": "Valerie McCray",
        "rep_candidate": "Jim Banks",
        "margin": 3778,
        "margin_pct": 10.08,
        "winner": "REP",
        "color": "#dc2626"
      },
      "26": {
        "dem_votes": 9164,
        "rep_votes": 6232,
        "other_votes": 377,
        "total_votes": 15773,
        "dem_candidate": "Valerie McCray",
        "rep_candidate": "Jim Banks",
        "margin": -2932,
        "margin_pct": -18.5887,
        "winner": "DEM",
        "color": "#2563eb"
      },
      "27": {
        "dem_votes": 12061,
        "rep_votes": 10400,
        "other_votes": 801,
        "total_votes": 23262,
        "dem_candidate": "Valerie McCray",
        "rep_candidate": "Jim Banks",
        "margin": -1661,
        "margin_pct": -7.1404,
        "winner": "DEM",
        "color": "#2563eb"
      },
      "28": {
        "dem_votes": 9255,
        "rep_votes": 23799,
        "other_votes": 1072,
        "total_votes": 34126,
        "dem_candidate": "Valerie McCray",
        "rep_candidate": "Jim Banks",
        "margin": 14544,
        "margin_pct": 42.6185,
        "winner": "REP",
        "color": "#dc2626"
      },
      "29": {
        "dem_votes": 16314,
        "rep_votes": 25306,
        "other_votes": 1177,
        "total_votes": 42797,
        "dem_candidate": "Valerie McCray",
        "rep_candidate": "Jim Banks",
        "margin": 8992,
        "margin_pct": 21.0108,
        "winner": "REP",
        "color": "#dc2626"
      },
      "30": {
        "dem_votes": 8361,
        "rep_votes": 16503,
        "other_votes": 878,
        "total_votes": 25742,
        "dem_candidate": "Valerie McCray",
        "rep_candidate": "Jim Banks",
        "margin": 8142,
        "margin_pct": 31.6292,
        "winner": "REP",
        "color": "#dc2626"
      },
      "31": {
        "dem_votes": 7541,
        "rep_votes": 19831,
        "other_votes": 682,
        "total_votes": 28054,
        "dem_candidate": "Valerie McCray",
        "rep_candidate": "Jim Banks",
        "margin": 12290,
        "margin_pct": 43.8084,
        "winner": "REP",
        "color": "#dc2626"
      },
      "32": {
        "dem_votes": 13786,
        "rep_votes": 12840,
        "other_votes": 716,
        "total_votes": 27342,
        "dem_candidate": "Valerie McCray",
        "rep_candidate": "Jim Banks",
        "margin": -946,
        "margin_pct": -3.4599,
        "winner": "DEM",
        "color": "#2563eb"
      },
      "33": {
        "dem_votes": 6753,
        "rep_votes": 21118,
        "other_votes": 803,
        "total_votes": 28674,
        "dem_candidate": "Valerie McCray",
        "rep_candidate": "Jim Banks",
        "margin": 14365,
        "margin_pct": 50.0976,
        "winner": "REP",
        "color": "#dc2626"
      },
      "34": {
        "dem_votes": 10967,
        "rep_votes": 10103,
        "other_votes": 652,
        "total_votes": 21722,
        "dem_candidate": "Valerie McCray",
        "rep_candidate": "Jim Banks",
        "margin": -864,
        "margin_pct": -3.9775,
        "winner": "DEM",
        "color": "#2563eb"
      },
      "35": {
        "dem_votes": 11482,
        "rep_votes": 26967,
        "other_votes": 1173,
        "total_votes": 39622,
        "dem_candidate": "Valerie McCray",
        "rep_candidate": "Jim Banks",
        "margin": 15485,
        "margin_pct": 39.0818,
        "winner": "REP",
        "color": "#dc2626"
      },
      "36": {
        "dem_votes": 4562,
        "rep_votes": 6076,
        "other_votes": 330,
        "total_votes": 10968,
        "dem_candidate": "Valerie McCray",
        "rep_candidate": "Jim Banks",
        "margin": 1514,
        "margin_pct": 13.8038,
        "winner": "REP",
        "color": "#dc2626"
      },
      "37": {
        "dem_votes": 23078,
        "rep_votes": 32637,
        "other_votes": 1423,
        "total_votes": 57138,
        "dem_candidate": "Valerie McCray",
        "rep_candidate": "Jim Banks",
        "margin": 9559,
        "margin_pct": 16.7297,
        "winner": "REP",
        "color": "#dc2626"
      },
      "38": {
        "dem_votes": 9289,
        "rep_votes": 28493,
        "other_votes": 1132,
        "total_votes": 38914,
        "dem_candidate": "Valerie McCray",
        "rep_candidate": "Jim Banks",
        "margin": 19204,
        "margin_pct": 49.3498,
        "winner": "REP",
        "color": "#dc2626"
      },
      "39": {
        "dem_votes": 4346,
        "rep_votes": 5221,
        "other_votes": 188,
        "total_votes": 9755,
        "dem_candidate": "Valerie McCray",
        "rep_candidate": "Jim Banks",
        "margin": 875,
        "margin_pct": 8.9698,
        "winner": "REP",
        "color": "#dc2626"
      },
      "40": {
        "dem_votes": 12077,
        "rep_votes": 16613,
        "other_votes": 839,
        "total_votes": 29529,
        "dem_candidate": "Valerie McCray",
        "rep_candidate": "Jim Banks",
        "margin": 4536,
        "margin_pct": 15.3612,
        "winner": "REP",
        "color": "#dc2626"
      },
      "41": {
        "dem_votes": 7833,
        "rep_votes": 19528,
        "other_votes": 998,
        "total_votes": 28359,
        "dem_candidate": "Valerie McCray",
        "rep_candidate": "Jim Banks",
        "margin": 11695,
        "margin_pct": 41.2391,
        "winner": "REP",
        "color": "#dc2626"
      },
      "42": {
        "dem_votes": 7307,
        "rep_votes": 21160,
        "other_votes": 796,
        "total_votes": 29263,
        "dem_candidate": "Valerie McCray",
        "rep_candidate": "Jim Banks",
        "margin": 13853,
        "margin_pct": 47.3396,
        "winner": "REP",
        "color": "#dc2626"
      },
      "43": {
        "dem_votes": 6773,
        "rep_votes": 7571,
        "other_votes": 383,
        "total_votes": 14727,
        "dem_candidate": "Valerie McCray",
        "rep_candidate": "Jim Banks",
        "margin": 798,
        "margin_pct": 5.4186,
        "winner": "REP",
        "color": "#dc2626"
      },
      "44": {
        "dem_votes": 6777,
        "rep_votes": 21434,
        "other_votes": 899,
        "total_votes": 29110,
        "dem_candidate": "Valerie McCray",
        "rep_candidate": "Jim Banks",
        "margin": 14657,
        "margin_pct": 50.3504,
        "winner": "REP",
        "color": "#dc2626"
      },
      "45": {
        "dem_votes": 6735,
        "rep_votes": 22342,
        "other_votes": 788,
        "total_votes": 29865,
        "dem_candidate": "Valerie McCray",
        "rep_candidate": "Jim Banks",
        "margin": 15607,
        "margin_pct": 52.2585,
        "winner": "REP",
        "color": "#dc2626"
      },
      "46": {
        "dem_votes": 12145,
        "rep_votes": 23838,
        "other_votes": 1317,
        "total_votes": 37300,
        "dem_candidate": "Valerie McCray",
        "rep_candidate": "Jim Banks",
        "margin": 11693,
        "margin_pct": 31.3485,
        "winner": "REP",
        "color": "#dc2626"
      },
      "47": {
        "dem_votes": 8851,
        "rep_votes": 24509,
        "other_votes": 1145,
        "total_votes": 34505,
        "dem_candidate": "Valerie McCray",
        "rep_candidate": "Jim Banks",
        "margin": 15658,
        "margin_pct": 45.3789,
        "winner": "REP",
        "color": "#dc2626"
      },
      "48": {
        "dem_votes": 8218,
        "rep_votes": 15548,
        "other_votes": 448,
        "total_votes": 24214,
        "dem_candidate": "Valerie McCray",
        "rep_candidate": "Jim Banks",
        "margin": 7330,
        "margin_pct": 30.2717,
        "winner": "REP",
        "color": "#dc2626"
      },
      "49": {
        "dem_votes": 7591,
        "rep_votes": 15013,
        "other_votes": 419,
        "total_votes": 23023,
        "dem_candidate": "Valerie McCray",
        "rep_candidate": "Jim Banks",
        "margin": 7422,
        "margin_pct": 32.2373,
        "winner": "REP",
        "color": "#dc2626"
      },
      "50": {
        "dem_votes": 7010,
        "rep_votes": 22868,
        "other_votes": 883,
        "total_votes": 30761,
        "dem_candidate": "Valerie McCray",
        "rep_candidate": "Jim Banks",
        "margin": 15858,
        "margin_pct": 51.5523,
        "winner": "REP",
        "color": "#dc2626"
      },
      "51": {
        "dem_votes": 5481,
        "rep_votes": 17503,
        "other_votes": 538,
        "total_votes": 23522,
        "dem_candidate": "Valerie McCray",
        "rep_candidate": "Jim Banks",
        "margin": 12022,
        "margin_pct": 51.1096,
        "winner": "REP",
        "color": "#dc2626"
      },
      "52": {
        "dem_votes": 6335,
        "rep_votes": 19504,
        "other_votes": 744,
        "total_votes": 26583,
        "dem_candidate": "Valerie McCray",
        "rep_candidate": "Jim Banks",
        "margin": 13169,
        "margin_pct": 49.5392,
        "winner": "REP",
        "color": "#dc2626"
      },
      "53": {
        "dem_votes": 9409,
        "rep_votes": 24361,
        "other_votes": 1561,
        "total_votes": 35331,
        "dem_candidate": "Valerie McCray",
        "rep_candidate": "Jim Banks",
        "margin": 14952,
        "margin_pct": 42.3198,
        "winner": "REP",
        "color": "#dc2626"
      },
      "54": {
        "dem_votes": 7041,
        "rep_votes": 22266,
        "other_votes": 975,
        "total_votes": 30282,
        "dem_candidate": "Valerie McCray",
        "rep_candidate": "Jim Banks",
        "margin": 15225,
        "margin_pct": 50.2774,
        "winner": "REP",
        "color": "#dc2626"
      },
      "55": {
        "dem_votes": 5549,
        "rep_votes": 22399,
        "other_votes": 746,
        "total_votes": 28694,
        "dem_candidate": "Valerie McCray",
        "rep_candidate": "Jim Banks",
        "margin": 16850,
        "margin_pct": 58.7231,
        "winner": "REP",
        "color": "#dc2626"
      },
      "56": {
        "dem_votes": 8432,
        "rep_votes": 17334,
        "other_votes": 910,
        "total_votes": 26676,
        "dem_candidate": "Valerie McCray",
        "rep_candidate": "Jim Banks",
        "margin": 8902,
        "margin_pct": 33.3708,
        "winner": "REP",
        "color": "#dc2626"
      },
      "57": {
        "dem_votes": 8799,
        "rep_votes": 18629,
        "other_votes": 857,
        "total_votes": 28285,
        "dem_candidate": "Valerie McCray",
        "rep_candidate": "Jim Banks",
        "margin": 9830,
        "margin_pct": 34.7534,
        "winner": "REP",
        "color": "#dc2626"
      },
      "58": {
        "dem_votes": 8144,
        "rep_votes": 16362,
        "other_votes": 858,
        "total_votes": 25364,
        "dem_candidate": "Valerie McCray",
        "rep_candidate": "Jim Banks",
        "margin": 8218,
        "margin_pct": 32.4003,
        "winner": "REP",
        "color": "#dc2626"
      },
      "59": {
        "dem_votes": 6256,
        "rep_votes": 10722,
        "other_votes": 468,
        "total_votes": 17446,
        "dem_candidate": "Valerie McCray",
        "rep_candidate": "Jim Banks",
        "margin": 4466,
        "margin_pct": 25.599,
        "winner": "REP",
        "color": "#dc2626"
      },
      "60": {
        "dem_votes": 8591,
        "rep_votes": 26847,
        "other_votes": 1198,
        "total_votes": 36636,
        "dem_candidate": "Valerie McCray",
        "rep_candidate": "Jim Banks",
        "margin": 18256,
        "margin_pct": 49.8308,
        "winner": "REP",
        "color": "#dc2626"
      },
      "61": {
        "dem_votes": 9812,
        "rep_votes": 2365,
        "other_votes": 272,
        "total_votes": 12449,
        "dem_candidate": "Valerie McCray",
        "rep_candidate": "Jim Banks",
        "margin": -7447,
        "margin_pct": -59.8201,
        "winner": "DEM",
        "color": "#2563eb"
      },
      "62": {
        "dem_votes": 21366,
        "rep_votes": 21601,
        "other_votes": 1342,
        "total_votes": 44309,
        "dem_candidate": "Valerie McCray",
        "rep_candidate": "Jim Banks",
        "margin": 235,
        "margin_pct": 0.5304,
        "winner": "REP",
        "color": "#dc2626"
      },
      "63": {
        "dem_votes": 6149,
        "rep_votes": 19875,
        "other_votes": 744,
        "total_votes": 26768,
        "dem_candidate": "Valerie McCray",
        "rep_candidate": "Jim Banks",
        "margin": 13726,
        "margin_pct": 51.2776,
        "winner": "REP",
        "color": "#dc2626"
      },
      "64": {
        "dem_votes": 8454,
        "rep_votes": 23772,
        "other_votes": 837,
        "total_votes": 33063,
        "dem_candidate": "Valerie McCray",
        "rep_candidate": "Jim Banks",
        "margin": 15318,
        "margin_pct": 46.3297,
        "winner": "REP",
        "color": "#dc2626"
      },
      "65": {
        "dem_votes": 7130,
        "rep_votes": 23334,
        "other_votes": 958,
        "total_votes": 31422,
        "dem_candidate": "Valerie McCray",
        "rep_candidate": "Jim Banks",
        "margin": 16204,
        "margin_pct": 51.569,
        "winner": "REP",
        "color": "#dc2626"
      },
      "66": {
        "dem_votes": 10156,
        "rep_votes": 22663,
        "other_votes": 1092,
        "total_votes": 33911,
        "dem_candidate": "Valerie McCray",
        "rep_candidate": "Jim Banks",
        "margin": 12507,
        "margin_pct": 36.8818,
        "winner": "REP",
        "color": "#dc2626"
      },
      "67": {
        "dem_votes": 7336,
        "rep_votes": 24133,
        "other_votes": 863,
        "total_votes": 32332,
        "dem_candidate": "Valerie McCray",
        "rep_candidate": "Jim Banks",
        "margin": 16797,
        "margin_pct": 51.9516,
        "winner": "REP",
        "color": "#dc2626"
      },
      "68": {
        "dem_votes": 7084,
        "rep_votes": 27041,
        "other_votes": 735,
        "total_votes": 34860,
        "dem_candidate": "Valerie McCray",
        "rep_candidate": "Jim Banks",
        "margin": 19957,
        "margin_pct": 57.249,
        "winner": "REP",
        "color": "#dc2626"
      },
      "69": {
        "dem_votes": 5987,
        "rep_votes": 18816,
        "other_votes": 672,
        "total_votes": 25475,
        "dem_candidate": "Valerie McCray",
        "rep_candidate": "Jim Banks",
        "margin": 12829,
        "margin_pct": 50.3592,
        "winner": "REP",
        "color": "#dc2626"
      },
      "70": {
        "dem_votes": 8228,
        "rep_votes": 22302,
        "other_votes": 899,
        "total_votes": 31429,
        "dem_candidate": "Valerie McCray",
        "rep_candidate": "Jim Banks",
        "margin": 14074,
        "margin_pct": 44.7803,
        "winner": "REP",
        "color": "#dc2626"
      },
      "71": {
        "dem_votes": 14554,
        "rep_votes": 14336,
        "other_votes": 971,
        "total_votes": 29861,
        "dem_candidate": "Valerie McCray",
        "rep_candidate": "Jim Banks",
        "margin": -218,
        "margin_pct": -0.73,
        "winner": "DEM",
        "color": "#2563eb"
      },
      "72": {
        "dem_votes": 14384,
        "rep_votes": 18711,
        "other_votes": 950,
        "total_votes": 34045,
        "dem_candidate": "Valerie McCray",
        "rep_candidate": "Jim Banks",
        "margin": 4327,
        "margin_pct": 12.7096,
        "winner": "REP",
        "color": "#dc2626"
      },
      "73": {
        "dem_votes": 7323,
        "rep_votes": 22588,
        "other_votes": 1104,
        "total_votes": 31015,
        "dem_candidate": "Valerie McCray",
        "rep_candidate": "Jim Banks",
        "margin": 15265,
        "margin_pct": 49.2181,
        "winner": "REP",
        "color": "#dc2626"
      },
      "74": {
        "dem_votes": 9297,
        "rep_votes": 21168,
        "other_votes": 774,
        "total_votes": 31239,
        "dem_candidate": "Valerie McCray",
        "rep_candidate": "Jim Banks",
        "margin": 11871,
        "margin_pct": 38.0006,
        "winner": "REP",
        "color": "#dc2626"
      },
      "75": {
        "dem_votes": 9860,
        "rep_votes": 22024,
        "other_votes": 764,
        "total_votes": 32648,
        "dem_candidate": "Valerie McCray",
        "rep_candidate": "Jim Banks",
        "margin": 12164,
        "margin_pct": 37.258,
        "winner": "REP",
        "color": "#dc2626"
      },
      "76": {
        "dem_votes": 11372,
        "rep_votes": 23613,
        "other_votes": 732,
        "total_votes": 35717,
        "dem_candidate": "Valerie McCray",
        "rep_candidate": "Jim Banks",
        "margin": 12241,
        "margin_pct": 34.2722,
        "winner": "REP",
        "color": "#dc2626"
      },
      "77": {
        "dem_votes": 8799,
        "rep_votes": 6946,
        "other_votes": 379,
        "total_votes": 16124,
        "dem_candidate": "Valerie McCray",
        "rep_candidate": "Jim Banks",
        "margin": -1853,
        "margin_pct": -11.4922,
        "winner": "DEM",
        "color": "#2563eb"
      },
      "78": {
        "dem_votes": 11262,
        "rep_votes": 17006,
        "other_votes": 556,
        "total_votes": 28824,
        "dem_candidate": "Valerie McCray",
        "rep_candidate": "Jim Banks",
        "margin": 5744,
        "margin_pct": 19.9278,
        "winner": "REP",
        "color": "#dc2626"
      },
      "79": {
        "dem_votes": 5141,
        "rep_votes": 20353,
        "other_votes": 693,
        "total_votes": 26187,
        "dem_candidate": "Valerie McCray",
        "rep_candidate": "Jim Banks",
        "margin": 15212,
        "margin_pct": 58.0899,
        "winner": "REP",
        "color": "#dc2626"
      },
      "80": {
        "dem_votes": 11063,
        "rep_votes": 5783,
        "other_votes": 400,
        "total_votes": 17246,
        "dem_candidate": "Valerie McCray",
        "rep_candidate": "Jim Banks",
        "margin": -5280,
        "margin_pct": -30.6158,
        "winner": "DEM",
        "color": "#2563eb"
      },
      "81": {
        "dem_votes": 10786,
        "rep_votes": 19383,
        "other_votes": 745,
        "total_votes": 30914,
        "dem_candidate": "Valerie McCray",
        "rep_candidate": "Jim Banks",
        "margin": 8597,
        "margin_pct": 27.8094,
        "winner": "REP",
        "color": "#dc2626"
      },
      "82": {
        "dem_votes": 11608,
        "rep_votes": 8868,
        "other_votes": 644,
        "total_votes": 21120,
        "dem_candidate": "Valerie McCray",
        "rep_candidate": "Jim Banks",
        "margin": -2740,
        "margin_pct": -12.9735,
        "winner": "DEM",
        "color": "#2563eb"
      },
      "83": {
        "dem_votes": 12113,
        "rep_votes": 21018,
        "other_votes": 818,
        "total_votes": 33949,
        "dem_candidate": "Valerie McCray",
        "rep_candidate": "Jim Banks",
        "margin": 8905,
        "margin_pct": 26.2305,
        "winner": "REP",
        "color": "#dc2626"
      },
      "84": {
        "dem_votes": 11688,
        "rep_votes": 18159,
        "other_votes": 662,
        "total_votes": 30509,
        "dem_candidate": "Valerie McCray",
        "rep_candidate": "Jim Banks",
        "margin": 6471,
        "margin_pct": 21.2101,
        "winner": "REP",
        "color": "#dc2626"
      },
      "85": {
        "dem_votes": 9040,
        "rep_votes": 23832,
        "other_votes": 760,
        "total_votes": 33632,
        "dem_candidate": "Valerie McCray",
        "rep_candidate": "Jim Banks",
        "margin": 14792,
        "margin_pct": 43.9819,
        "winner": "REP",
        "color": "#dc2626"
      },
      "86": {
        "dem_votes": 20613,
        "rep_votes": 8519,
        "other_votes": 634,
        "total_votes": 29766,
        "dem_candidate": "Valerie McCray",
        "rep_candidate": "Jim Banks",
        "margin": -12094,
        "margin_pct": -40.6302,
        "winner": "DEM",
        "color": "#2563eb"
      },
      "87": {
        "dem_votes": 17868,
        "rep_votes": 10668,
        "other_votes": 636,
        "total_votes": 29172,
        "dem_candidate": "Valerie McCray",
        "rep_candidate": "Jim Banks",
        "margin": -7200,
        "margin_pct": -24.6812,
        "winner": "DEM",
        "color": "#2563eb"
      },
      "88": {
        "dem_votes": 16670,
        "rep_votes": 22335,
        "other_votes": 1115,
        "total_votes": 40120,
        "dem_candidate": "Valerie McCray",
        "rep_candidate": "Jim Banks",
        "margin": 5665,
        "margin_pct": 14.1201,
        "winner": "REP",
        "color": "#dc2626"
      },
      "89": {
        "dem_votes": 16969,
        "rep_votes": 14943,
        "other_votes": 821,
        "total_votes": 32733,
        "dem_candidate": "Valerie McCray",
        "rep_candidate": "Jim Banks",
        "margin": -2026,
        "margin_pct": -6.1895,
        "winner": "DEM",
        "color": "#2563eb"
      },
      "90": {
        "dem_votes": 13384,
        "rep_votes": 21423,
        "other_votes": 922,
        "total_votes": 35729,
        "dem_candidate": "Valerie McCray",
        "rep_candidate": "Jim Banks",
        "margin": 8039,
        "margin_pct": 22.4999,
        "winner": "REP",
        "color": "#dc2626"
      },
      "91": {
        "dem_votes": 18953,
        "rep_votes": 29314,
        "other_votes": 1595,
        "total_votes": 49862,
        "dem_candidate": "Valerie McCray",
        "rep_candidate": "Jim Banks",
        "margin": 10361,
        "margin_pct": 20.7794,
        "winner": "REP",
        "color": "#dc2626"
      },
      "92": {
        "dem_votes": 14293,
        "rep_votes": 10552,
        "other_votes": 705,
        "total_votes": 25550,
        "dem_candidate": "Valerie McCray",
        "rep_candidate": "Jim Banks",
        "margin": -3741,
        "margin_pct": -14.6419,
        "winner": "DEM",
        "color": "#2563eb"
      },
      "93": {
        "dem_votes": 7232,
        "rep_votes": 10804,
        "other_votes": 499,
        "total_votes": 18535,
        "dem_candidate": "Valerie McCray",
        "rep_candidate": "Jim Banks",
        "margin": 3572,
        "margin_pct": 19.2716,
        "winner": "REP",
        "color": "#dc2626"
      },
      "94": {
        "dem_votes": 12127,
        "rep_votes": 2367,
        "other_votes": 243,
        "total_votes": 14737,
        "dem_candidate": "Valerie McCray",
        "rep_candidate": "Jim Banks",
        "margin": -9760,
        "margin_pct": -66.2279,
        "winner": "DEM",
        "color": "#2563eb"
      },
      "95": {
        "dem_votes": 12997,
        "rep_votes": 4494,
        "other_votes": 342,
        "total_votes": 17833,
        "dem_candidate": "Valerie McCray",
        "rep_candidate": "Jim Banks",
        "margin": -8503,
        "margin_pct": -47.6813,
        "winner": "DEM",
        "color": "#2563eb"
      },
      "96": {
        "dem_votes": 14465,
        "rep_votes": 2600,
        "other_votes": 359,
        "total_votes": 17424,
        "dem_candidate": "Valerie McCray",
        "rep_candidate": "Jim Banks",
        "margin": -11865,
        "margin_pct": -68.0957,
        "winner": "DEM",
        "color": "#2563eb"
      },
      "97": {
        "dem_votes": 12920,
        "rep_votes": 9654,
        "other_votes": 639,
        "total_votes": 23213,
        "dem_candidate": "Valerie McCray",
        "rep_candidate": "Jim Banks",
        "margin": -3266,
        "margin_pct": -14.0697,
        "winner": "DEM",
        "color": "#2563eb"
      },
      "98": {
        "dem_votes": 14347,
        "rep_votes": 3197,
        "other_votes": 367,
        "total_votes": 17911,
        "dem_candidate": "Valerie McCray",
        "rep_candidate": "Jim Banks",
        "margin": -11150,
        "margin_pct": -62.2522,
        "winner": "DEM",
        "color": "#2563eb"
      },
      "99": {
        "dem_votes": 13252,
        "rep_votes": 3105,
        "other_votes": 397,
        "total_votes": 16754,
        "dem_candidate": "Valerie McCray",
        "rep_candidate": "Jim Banks",
        "margin": -10147,
        "margin_pct": -60.5646,
        "winner": "DEM",
        "color": "#2563eb"
      },
      "100": {
        "dem_votes": 9314,
        "rep_votes": 3690,
        "other_votes": 384,
        "total_votes": 13388,
        "dem_candidate": "Valerie McCray",
        "rep_candidate": "Jim Banks",
        "margin": -5624,
        "margin_pct": -42.0078,
        "winner": "DEM",
        "color": "#2563eb"
      }
    }
  }
}
