{"meta":{"scope":"state_house","contest_type":"secretary_of_state","year":2022,"districts":54,"match_coverage_pct":38.04,"allocation":"county_area_weighted_from_statewide_contest"},"general":{"results":{"1":{"dem_votes":2720,"rep_votes":2254,"other_votes":147,"total_votes":5121,"dem_candidate":"Destiny Wells","rep_candidate":"Diego Morales","margin":-466,"margin_pct":-9.0998,"winner":"DEM","color":"#2563eb"},"2":{"dem_votes":4787,"rep_votes":3968,"other_votes":258,"total_votes":9013,"dem_candidate":"Destiny Wells","rep_candidate":"Diego Morales","margin":-819,"margin_pct":-9.0869,"winner":"DEM","color":"#2563eb"},"3":{"dem_votes":18974,"rep_votes":15725,"other_votes":1024,"total_votes":35723,"dem_candidate":"Destiny Wells","rep_candidate":"Diego Morales","margin":-3249,"margin_pct":-9.095,"winner":"DEM","color":"#2563eb"},"11":{"dem_votes":21546,"rep_votes":17857,"other_votes":1163,"total_votes":40566,"dem_candidate":"Destiny Wells","rep_candidate":"Diego Morales","margin":-3689,"margin_pct":-9.0938,"winner":"DEM","color":"#2563eb"},"12":{"dem_votes":2791,"rep_votes":2313,"other_votes":151,"total_votes":5255,"dem_candidate":"Destiny Wells","rep_candidate":"Diego Morales","margin":-478,"margin_pct":-9.0961,"winner":"DEM","color":"#2563eb"},"14":{"dem_votes":4258,"rep_votes":3529,"other_votes":230,"total_votes":8017,"dem_candidate":"Destiny Wells","rep_candidate":"Diego Morales","margin":-729,"margin_pct":-9.0932,"winner":"DEM","color":"#2563eb"},"15":{"dem_votes":5100,"rep_votes":4227,"other_votes":275,"total_votes":9602,"dem_candidate":"Destiny Wells","rep_candidate":"Diego Morales","margin":-873,"margin_pct":-9.0919,"winner":"DEM","color":"#2563eb"},"18":{"dem_votes":1872,"rep_votes":5849,"other_votes":454,"total_votes":8175,"dem_candidate":"Destiny Wells","rep_candidate":"Diego Morales","margin":3977,"margin_pct":48.6483,"winner":"REP","color":"#dc2626"},"19":{"dem_votes":10237,"rep_votes":8484,"other_votes":552,"total_votes":19273,"dem_candidate":"Destiny Wells","rep_candidate":"Diego Morales","margin":-1753,"margin_pct":-9.0956,"winner":"DEM","color":"#2563eb"},"22":{"dem_votes":4385,"rep_votes":15371,"other_votes":1148,"total_votes":20904,"dem_candidate":"Destiny Wells","rep_candidate":"Diego Morales","margin":10986,"margin_pct":52.5545,"winner":"REP","color":"#dc2626"},"23":{"dem_votes":1804,"rep_votes":5776,"other_votes":373,"total_votes":7953,"dem_candidate":"Destiny Wells","rep_candidate":"Diego Morales","margin":3972,"margin_pct":49.9434,"winner":"REP","color":"#dc2626"},"24":{"dem_votes":15630,"rep_votes":17110,"other_votes":2983,"total_votes":35723,"dem_candidate":"Destiny Wells","rep_candidate":"Diego Morales","margin":1480,"margin_pct":4.143,"winner":"REP","color":"#dc2626"},"25":{"dem_votes":1508,"rep_votes":2161,"other_votes":435,"total_votes":4104,"dem_candidate":"Destiny Wells","rep_candidate":"Diego Morales","margin":653,"margin_pct":15.9113,"winner":"REP","color":"#dc2626"},"28":{"dem_votes":13145,"rep_votes":18835,"other_votes":3795,"total_votes":35775,"dem_candidate":"Destiny Wells","rep_candidate":"Diego Morales","margin":5690,"margin_pct":15.905,"winner":"REP","color":"#dc2626"},"29":{"dem_votes":6957,"rep_votes":7616,"other_votes":1328,"total_votes":15901,"dem_candidate":"Destiny Wells","rep_candidate":"Diego Morales","margin":659,"margin_pct":4.1444,"winner":"REP","color":"#dc2626"},"30":{"dem_votes":4941,"rep_votes":9355,"other_votes":869,"total_votes":15165,"dem_candidate":"Destiny Wells","rep_candidate":"Diego Morales","margin":4414,"margin_pct":29.1065,"winner":"REP","color":"#dc2626"},"31":{"dem_votes":6550,"rep_votes":13243,"other_votes":1196,"total_votes":20989,"dem_candidate":"Destiny Wells","rep_candidate":"Diego Morales","margin":6693,"margin_pct":31.8881,"winner":"REP","color":"#dc2626"},"32":{"dem_votes":4277,"rep_votes":4682,"other_votes":816,"total_votes":9775,"dem_candidate":"Destiny Wells","rep_candidate":"Diego Morales","margin":405,"margin_pct":4.1432,"winner":"REP","color":"#dc2626"},"33":{"dem_votes":5207,"rep_votes":6353,"other_votes":748,"total_votes":12308,"dem_candidate":"Destiny Wells","rep_candidate":"Diego Morales","margin":1146,"margin_pct":9.311,"winner":"REP","color":"#dc2626"},"34":{"dem_votes":1330,"rep_votes":1576,"other_votes":181,"total_votes":3087,"dem_candidate":"Destiny Wells","rep_candidate":"Diego Morales","margin":246,"margin_pct":7.9689,"winner":"REP","color":"#dc2626"},"35":{"dem_votes":13245,"rep_votes":16641,"other_votes":2170,"total_votes":32056,"dem_candidate":"Destiny Wells","rep_candidate":"Diego Morales","margin":3396,"margin_pct":10.594,"winner":"REP","color":"#dc2626"},"36":{"dem_votes":2860,"rep_votes":3791,"other_votes":545,"total_votes":7196,"dem_candidate":"Destiny Wells","rep_candidate":"Diego Morales","margin":931,"margin_pct":12.9377,"winner":"REP","color":"#dc2626"},"37":{"dem_votes":23876,"rep_votes":26137,"other_votes":4557,"total_votes":54570,"dem_candidate":"Destiny Wells","rep_candidate":"Diego Morales","margin":2261,"margin_pct":4.1433,"winner":"REP","color":"#dc2626"},"38":{"dem_votes":4070,"rep_votes":8121,"other_votes":774,"total_votes":12965,"dem_candidate":"Destiny Wells","rep_candidate":"Diego Morales","margin":4051,"margin_pct":31.2457,"winner":"REP","color":"#dc2626"},"39":{"dem_votes":3931,"rep_votes":4304,"other_votes":750,"total_votes":8985,"dem_candidate":"Destiny Wells","rep_candidate":"Diego Morales","margin":373,"margin_pct":4.1514,"winner":"REP","color":"#dc2626"},"40":{"dem_votes":1885,"rep_votes":2701,"other_votes":544,"total_votes":5130,"dem_candidate":"Destiny Wells","rep_candidate":"Diego Morales","margin":816,"margin_pct":15.9064,"winner":"REP","color":"#dc2626"},"41":{"dem_votes":1176,"rep_votes":3168,"other_votes":313,"total_votes":4657,"dem_candidate":"Destiny Wells","rep_candidate":"Diego Morales","margin":1992,"margin_pct":42.7743,"winner":"REP","color":"#dc2626"},"45":{"dem_votes":2915,"rep_votes":6738,"other_votes":558,"total_votes":10211,"dem_candidate":"Destiny Wells","rep_candidate":"Diego Morales","margin":3823,"margin_pct":37.44,"winner":"REP","color":"#dc2626"},"47":{"dem_votes":9596,"rep_votes":17355,"other_votes":2908,"total_votes":29859,"dem_candidate":"Destiny Wells","rep_candidate":"Diego Morales","margin":7759,"margin_pct":25.9855,"winner":"REP","color":"#dc2626"},"50":{"dem_votes":5083,"rep_votes":15138,"other_votes":896,"total_votes":21117,"dem_candidate":"Destiny Wells","rep_candidate":"Diego Morales","margin":10055,"margin_pct":47.6157,"winner":"REP","color":"#dc2626"},"51":{"dem_votes":1373,"rep_votes":4884,"other_votes":289,"total_votes":6546,"dem_candidate":"Destiny Wells","rep_candidate":"Diego Morales","margin":3511,"margin_pct":53.6358,"winner":"REP","color":"#dc2626"},"52":{"dem_votes":3048,"rep_votes":8022,"other_votes":541,"total_votes":11611,"dem_candidate":"Destiny Wells","rep_candidate":"Diego Morales","margin":4974,"margin_pct":42.8387,"winner":"REP","color":"#dc2626"},"53":{"dem_votes":1317,"rep_votes":1745,"other_votes":251,"total_votes":3313,"dem_candidate":"Destiny Wells","rep_candidate":"Diego Morales","margin":428,"margin_pct":12.9188,"winner":"REP","color":"#dc2626"},"54":{"dem_votes":4565,"rep_votes":10250,"other_votes":1654,"total_votes":16469,"dem_candidate":"Destiny Wells","rep_candidate":"Diego Morales","margin":5685,"margin_pct":34.5194,"winner":"REP","color":"#dc2626"},"55":{"dem_votes":2370,"rep_votes":8987,"other_votes":735,"total_votes":12092,"dem_candidate":"Destiny Wells","rep_candidate":"Diego Morales","margin":6617,"margin_pct":54.7221,"winner":"REP","color":"#dc2626"},"56":{"dem_votes":212,"rep_votes":448,"other_votes":70,"total_votes":730,"dem_candidate":"Destiny Wells","rep_candidate":"Diego Morales","margin":236,"margin_pct":32.3288,"winner":"REP","color":"#dc2626"},"57":{"dem_votes":2427,"rep_votes":4312,"other_votes":804,"total_votes":7543,"dem_candidate":"Destiny Wells","rep_candidate":"Diego Morales","margin":1885,"margin_pct":24.9901,"winner":"REP","color":"#dc2626"},"58":{"dem_votes":3151,"rep_votes":5699,"other_votes":955,"total_votes":9805,"dem_candidate":"Destiny Wells","rep_candidate":"Diego Morales","margin":2548,"margin_pct":25.9867,"winner":"REP","color":"#dc2626"},"59":{"dem_votes":4424,"rep_votes":6784,"other_votes":901,"total_votes":12109,"dem_candidate":"Destiny Wells","rep_candidate":"Diego Morales","margin":2360,"margin_pct":19.4896,"winner":"REP","color":"#dc2626"},"60":{"dem_votes":5489,"rep_votes":13848,"other_votes":2542,"total_votes":21879,"dem_candidate":"Destiny Wells","rep_candidate":"Diego Morales","margin":8359,"margin_pct":38.2056,"winner":"REP","color":"#dc2626"},"63":{"dem_votes":995,"rep_votes":2972,"other_votes":228,"total_votes":4195,"dem_candidate":"Destiny Wells","rep_candidate":"Diego Morales","margin":1977,"margin_pct":47.1275,"winner":"REP","color":"#dc2626"},"64":{"dem_votes":1605,"rep_votes":4095,"other_votes":269,"total_votes":5969,"dem_candidate":"Destiny Wells","rep_candidate":"Diego Morales","margin":2490,"margin_pct":41.7155,"winner":"REP","color":"#dc2626"},"66":{"dem_votes":10575,"rep_votes":16067,"other_votes":1008,"total_votes":27650,"dem_candidate":"Destiny Wells","rep_candidate":"Diego Morales","margin":5492,"margin_pct":19.8626,"winner":"REP","color":"#dc2626"},"67":{"dem_votes":4284,"rep_votes":10200,"other_votes":1005,"total_votes":15489,"dem_candidate":"Destiny Wells","rep_candidate":"Diego Morales","margin":5916,"margin_pct":38.1948,"winner":"REP","color":"#dc2626"},"68":{"dem_votes":3038,"rep_votes":11688,"other_votes":474,"total_votes":15200,"dem_candidate":"Destiny Wells","rep_candidate":"Diego Morales","margin":8650,"margin_pct":56.9079,"winner":"REP","color":"#dc2626"},"69":{"dem_votes":411,"rep_votes":631,"other_votes":84,"total_votes":1126,"dem_candidate":"Destiny Wells","rep_candidate":"Diego Morales","margin":220,"margin_pct":19.5382,"winner":"REP","color":"#dc2626"},"70":{"dem_votes":6132,"rep_votes":13243,"other_votes":679,"total_votes":20054,"dem_candidate":"Destiny Wells","rep_candidate":"Diego Morales","margin":7111,"margin_pct":35.4593,"winner":"REP","color":"#dc2626"},"71":{"dem_votes":1372,"rep_votes":2062,"other_votes":130,"total_votes":3564,"dem_candidate":"Destiny Wells","rep_candidate":"Diego Morales","margin":690,"margin_pct":19.3603,"winner":"REP","color":"#dc2626"},"73":{"dem_votes":4531,"rep_votes":8922,"other_votes":1237,"total_votes":14690,"dem_candidate":"Destiny Wells","rep_candidate":"Diego Morales","margin":4391,"margin_pct":29.8911,"winner":"REP","color":"#dc2626"},"75":{"dem_votes":688,"rep_votes":2043,"other_votes":102,"total_votes":2833,"dem_candidate":"Destiny Wells","rep_candidate":"Diego Morales","margin":1355,"margin_pct":47.8292,"winner":"REP","color":"#dc2626"},"76":{"dem_votes":2414,"rep_votes":5854,"other_votes":369,"total_votes":8637,"dem_candidate":"Destiny Wells","rep_candidate":"Diego Morales","margin":3440,"margin_pct":39.8286,"winner":"REP","color":"#dc2626"},"79":{"dem_votes":3780,"rep_votes":12635,"other_votes":649,"total_votes":17064,"dem_candidate":"Destiny Wells","rep_candidate":"Diego Morales","margin":8855,"margin_pct":51.8929,"winner":"REP","color":"#dc2626"},"83":{"dem_votes":1471,"rep_votes":4314,"other_votes":340,"total_votes":6125,"dem_candidate":"Destiny Wells","rep_candidate":"Diego Morales","margin":2843,"margin_pct":46.4163,"winner":"REP","color":"#dc2626"},"88":{"dem_votes":2239,"rep_votes":2624,"other_votes":427,"total_votes":5290,"dem_candidate":"Destiny Wells","rep_candidate":"Diego Morales","margin":385,"margin_pct":7.2779,"winner":"REP","color":"#dc2626"}}}}